configloader-1.0.1.dist-info/top_level.txt
configloader-1.0.1.dist-info/RECORD
configloader-1.0.1.dist-info/METADATA
configloader-1.0.1.dist-info/pbr.json
configloader-1.0.1.dist-info/DESCRIPTION.rst
configloader-1.0.1.dist-info/metadata.json
configloader-1.0.1.dist-info/WHEEL
configloader/__init__.py
