Metadata-Version: 1.1
Name: configloader
Version: 1.0.1
Summary: Python dict that supports common app configuration-loading scenarios.
Home-page: https://github.com/adblair/configloader
Author: Arthur Blair
Author-email: adblair@gmail.com
License: MIT
Keywords: configloader
Platform: UNKNOWN
Classifier: Development Status :: 4 - Beta
Classifier: Intended Audience :: Developers
Classifier: License :: OSI Approved :: MIT License
Classifier: Natural Language :: English
Classifier: Programming Language :: Python :: 2
Classifier: Programming Language :: Python :: 2.6
Classifier: Programming Language :: Python :: 2.7
Classifier: Programming Language :: Python :: 3
Classifier: Programming Language :: Python :: 3.3
Classifier: Programming Language :: Python :: 3.4
